inkpot/__init__.py
inkpot/__main__.py
inkpot/astunparse.py
inkpot/config.py
inkpot/directory.py
inkpot/file.py
inkpot-2.2.7.dist-info/LICENSE.txt
inkpot-2.2.7.dist-info/METADATA
inkpot-2.2.7.dist-info/WHEEL
inkpot-2.2.7.dist-info/top_level.txt
inkpot-2.2.7.dist-info/RECORD
