Metadata-Version: 2.1
Name: inkpot
Version: 2.2.7
Summary: a small simple library for generating documentation from docstrings
Home-page: https://github.com/AxelGard/inkpot
Author: Axel Gard
Author-email: axel.gard@tutanota.com
License: MIT
Classifier: Development Status :: 5 - Production/Stable
Classifier: Topic :: Documentation
Classifier: Topic :: Software Development :: Documentation
Classifier: License :: OSI Approved :: MIT License
Classifier: Programming Language :: Python :: 3.6
Classifier: Programming Language :: Python :: 3.7
Classifier: Programming Language :: Python :: 3.8
License-File: LICENSE.txt
Requires-Dist: six ==1.16.0
